rmq_client/__init__.py
rmq_client/client.py
rmq_client/config.py
rmq_client/exceptions.py
rmq_client/retry.py
rmq_client/sync.py
rmq_client-0.1.0.dist-info/METADATA
rmq_client-0.1.0.dist-info/WHEEL
rmq_client-0.1.0.dist-info/RECORD
